[
  {
    "scene_start_line": 1,
    "scene_end_line": 19,
    "time_in_story": "当日（紧接上章）",
    "location": "皇城内小道",
    "characters_present": [
      "王枫",
      "姜寒汐",
      "萧浩",
      "楚妍儿",
      "张叔"
    ],
    "summary": "姜寒汐倒数逼王枫起身，王枫见威胁已过立刻跳起装惊喜。楚妍儿骂王枫有脑疾，萧浩替师父回怼，双方对喷。姜寒汐看了一会闹剧后使用遁法悄然离去。"
  },
  {
    "scene_start_line": 20,
    "scene_end_line": 53,
    "time_in_story": "片刻后",
    "location": "皇城内小道",
    "characters_present": [
      "王枫",
      "萧浩",
      "楚妍儿",
      "张叔"
    ],
    "summary": "张叔发现姜寒汐消失，判断她是结灵境强者。他出面要求王枫二人束手就擒。王枫发现姜寒汐已走，不再伪装，爆发结灵境六层气息威慑张叔。楚妍儿恍然大悟王枫之前是在姜寒汐面前装弱。张叔识趣抱拳告退，拉着楚妍儿逃离。"
  },
  {
    "scene_start_line": 54,
    "scene_end_line": 71,
    "time_in_story": "随后",
    "location": "皇城小道外",
    "characters_present": [
      "王枫",
      "萧浩"
    ],
    "summary": "萧浩夸师父气势吓跑对方，王枫踢他屁股让他走。萧浩跟上后回味与楚妍儿对喷的场景，觉得少女生气的模样挺可爱，忍不住傻笑，王枫一头雾水。"
  },
  {
    "scene_start_line": 72,
    "scene_end_line": 99,
    "time_in_story": "当日稍晚",
    "location": "皇城皇宫·女帝寝殿",
    "characters_present": [
      "楚妍儿",
      "女帝（楚妍儿之母）"
    ],
    "summary": "楚妍儿回宫后向母亲女帝告状，称被两个男子辱骂。女帝神色凝重追问，楚妍儿鼓起勇气说出对方嘲讽她没断奶。女帝忍不住捂嘴笑出声，反问妍儿是否先骂了人家，楚妍儿语塞。"
  }
]